{
  "appPageId" : "1663b0ed-0fc3-497c-893d-8c06e82a7ad6",
  "componentName" : "siteforce:sldsTwoCol84Layout",
  "id" : "2b954607-6d80-4410-855c-30430e00f7ad",
  "label" : "Feed Detail",
  "regions" : [ {
    "id" : "0717bffd-190f-47c0-9064-9afa2b488fbf",
    "regionName" : "header",
    "type" : "region"
  }, {
    "components" : [ {
      "componentAttributes" : {
        "id" : "{!recordId}"
      },
      "componentName" : "forceCommunity:feedItemDetail",
      "id" : "cb7caa6f-48e6-48cf-9ef8-cd81c64099bf",
      "renderPriority" : "NEUTRAL",
      "renditionMap" : { },
      "type" : "component"
    } ],
    "id" : "c911eb67-a362-4b9b-b8d0-7585d6e828af",
    "regionName" : "content",
    "type" : "region"
  }, {
    "id" : "63415e48-5873-4ab2-96db-18bca2ca3175",
    "regionName" : "sidebar",
    "type" : "region"
  }, {
    "id" : "f2d0aa5e-43b1-4d7c-a991-e6e2ddc9b821",
    "regionName" : "footer",
    "type" : "region"
  } ],
  "themeLayoutType" : "Inner",
  "type" : "view",
  "viewType" : "feeditem-generic"
}